curseofaros/__init__.py
curseofaros/_assets/__init__.py
curseofaros/_assets/_client.py
curseofaros/_assets/errors.py
curseofaros-0.0.1.dist-info/LICENSE
curseofaros-0.0.1.dist-info/METADATA
curseofaros-0.0.1.dist-info/WHEEL
curseofaros-0.0.1.dist-info/top_level.txt
curseofaros-0.0.1.dist-info/RECORD
