Metadata-Version: 2.1
Name: curseofaros
Version: 0.0.1
Summary: A python wrapper for Curse Of Aros game leaderboards.
Home-page: https://github.com/Blank-c/Curse-Of-Aros-API
Author: Blank-c
Keywords: curseofaros
License-File: LICENSE
Requires-Dist: aiohttp
